GoSync/DriveUsageBox.py
GoSync/GoSync.py
GoSync/GoSyncController.py
GoSync/GoSyncDriveTree.py
GoSync/GoSyncEvents.py
GoSync/GoSyncModel.py
GoSync/GoSyncSelectionPage.py
GoSync/GoSyncSettingPage.py
GoSync/GoSyncUtils.py
GoSync/__init__.py
GoSync/defines.py
GoSync/resources/GoSyncIcon-16.png
GoSync/resources/GoSyncIcon-32.png
GoSync/resources/GoSyncIcon-64.png
GoSync/resources/GoSyncIcon.png
GoSync/resources/exit.png
GoSync/resources/info.png
GoSync/resources/settings.png
GoSync/resources/sync-menu.png
GoSync/resources/usage.png
GoSync/resources/user.png
GoSync-0.53.dist-info/LICENSE
GoSync-0.53.dist-info/METADATA
GoSync-0.53.dist-info/WHEEL
GoSync-0.53.dist-info/entry_points.txt
GoSync-0.53.dist-info/top_level.txt
GoSync-0.53.dist-info/RECORD
