Metadata-Version: 2.1
Name: GoSync
Version: 0.53
Summary: GoSync is an open source Google Drive client written in python.
Home-page: http://www.nulltrace.org/p/gosync.html
Author: Himanshu Chauhan, Alain Robillard
Author-email: hschauhan@nulltrace.org, arentoine@gmail.com
License: GPL
Keywords: Google Drive client Linux Python
Platform: UNKNOWN
Classifier: Development Status :: 3 - Alpha
Classifier: Intended Audience :: End Users/Desktop
Classifier: License :: OSI Approved :: GNU General Public License v2 or later (GPLv2+)
Classifier: Programming Language :: Python :: 3.6
Classifier: Topic :: Internet :: WWW/HTTP :: Dynamic Content
Requires-Dist: google-api-python-client
Requires-Dist: google-auth-httplib2
Requires-Dist: google-auth-oauthlib
Requires-Dist: watchdog
Requires-Dist: wxpython (>=4.1.0)
